memory_inventory/__init__.py
memory_inventory/__main__.py
memory_inventory/py.typed
memory_inventory-1.2.dist-info/METADATA
memory_inventory-1.2.dist-info/WHEEL
memory_inventory-1.2.dist-info/top_level.txt
memory_inventory-1.2.dist-info/RECORD
