Metadata-Version: 2.4
Name: memory_inventory
Version: 1.2
Summary: Inventory the long-lived Python objects in a process.
License-Expression: EUPL-1.2
Project-URL: Repository, https://github.com/liberapay/memory_inventory.py
Requires-Python: >=3.12
